qldata/__init__.py
qldata/_version.py
qldata/adapters/__init__.py
qldata/adapters/decorators.py
qldata/adapters/brokers/__init__.py
qldata/adapters/brokers/base.py
qldata/adapters/brokers/binance/__init__.py
qldata/adapters/brokers/binance/adapter.py
qldata/adapters/brokers/bybit/__init__.py
qldata/adapters/brokers/bybit/adapter.py
qldata/api/__init__.py
qldata/api/config/__init__.py
qldata/api/config/resilience.py
qldata/api/config/settings.py
qldata/api/core/__init__.py
qldata/api/core/streaming_api.py
qldata/api/core/unified.py
qldata/api/queries/__init__.py
qldata/api/queries/helpers.py
qldata/api/queries/multi_symbol.py
qldata/api/queries/symbol.py
qldata/api/reference/__init__.py
qldata/api/reference/symbols.py
qldata/api/sessions/__init__.py
qldata/api/sessions/query.py
qldata/api/sessions/stream.py
qldata/common/__init__.py
qldata/common/cache.py
qldata/common/logger.py
qldata/common/rate_limiter.py
qldata/common/dataframe/schema.py
qldata/common/dataframe/timestamps.py
qldata/common/io/__init__.py
qldata/common/io/paths.py
qldata/common/numeric/__init__.py
qldata/common/numeric/decimal_ops.py
qldata/common/strings/__init__.py
qldata/common/strings/symbols.py
qldata/common/time/__init__.py
qldata/common/time/parsing.py
qldata/common/time/zones.py
qldata/config/__init__.py
qldata/config/defaults.py
qldata/config/manager.py
qldata/errors/__init__.py
qldata/errors/api.py
qldata/errors/base.py
qldata/errors/data.py
qldata/errors/source.py
qldata/errors/store.py
qldata/errors/validation.py
qldata/logging/__init__.py
qldata/logging/setup.py
qldata/models/__init__.py
qldata/models/bar.py
qldata/models/dataset_metadata.py
qldata/models/funding.py
qldata/models/liquidation.py
qldata/models/mark_price.py
qldata/models/metadata.py
qldata/models/orderbook.py
qldata/models/quote.py
qldata/models/symbol_info.py
qldata/models/tick.py
qldata/models/timeframe.py
qldata/models/converters/__init__.py
qldata/models/converters/from_dataframe.py
qldata-0.3.0.dist-info/licenses/LICENSE
qldata-0.3.0.dist-info/METADATA
qldata-0.3.0.dist-info/WHEEL
qldata-0.3.0.dist-info/top_level.txt
qldata-0.3.0.dist-info/RECORD
