Metadata-Version: 2.4
Name: qldata
Version: 0.3.0
Summary: Python library for acquiring, storing, transforming, and validating market data
Author: ZENTCH-Q
License: MIT
Project-URL: Homepage, https://zentch-q.github.io/qldata-docs/
Project-URL: Documentation, https://zentch-q.github.io/qldata-docs/user-guide/installation/
Project-URL: Repository, https://github.com/ZENTCH-Q/qldata-docs
Keywords: quantitative,finance,market-data,trading,backtesting,crypto
Classifier: Development Status :: 3 - Alpha
Classifier: Intended Audience :: Developers
Classifier: Intended Audience :: Financial and Insurance Industry
Classifier: License :: OSI Approved :: MIT License
Classifier: Programming Language :: Python :: 3
Classifier: Programming Language :: Python :: 3.10
Classifier: Programming Language :: Python :: 3.11
Classifier: Programming Language :: Python :: 3.12
Classifier: Topic :: Office/Business :: Financial :: Investment
Classifier: Topic :: Scientific/Engineering
Classifier: Topic :: Software Development :: Libraries :: Python Modules
Requires-Python: >=3.10
License-File: LICENSE
Requires-Dist: pandas>=2.0.0
Requires-Dist: numpy>=1.24.0
Requires-Dist: pyarrow>=12.0.0
Requires-Dist: python-dateutil>=2.8.0
Requires-Dist: python-binance>=1.0.0
Requires-Dist: pybit>=5.0.0
Requires-Dist: duckdb>=0.9.0
Requires-Dist: websockets<14.0,>=12.0
Requires-Dist: aiohttp>=3.9.0
Requires-Dist: tenacity>=8.0.0
Provides-Extra: dev
Requires-Dist: pytest>=7.0; extra == "dev"
Requires-Dist: pytest-cov>=4.0; extra == "dev"
Requires-Dist: pytest-asyncio>=0.21.0; extra == "dev"
Requires-Dist: black>=23.0; extra == "dev"
Requires-Dist: ruff>=0.1.0; extra == "dev"
Requires-Dist: mypy>=1.0; extra == "dev"
Requires-Dist: pre-commit>=3.0; extra == "dev"
Requires-Dist: ipython>=8.0; extra == "dev"
Requires-Dist: jupyter>=1.0; extra == "dev"
Requires-Dist: mkdocs-material>=9.0.0; extra == "dev"
Requires-Dist: mkdocstrings[python]>=0.20.0; extra == "dev"
Provides-Extra: minimal
Requires-Dist: pandas>=2.0.0; extra == "minimal"
Requires-Dist: numpy>=1.24.0; extra == "minimal"
Requires-Dist: python-dateutil>=2.8.0; extra == "minimal"
Provides-Extra: binance
Requires-Dist: python-binance>=1.0.0; extra == "binance"
Requires-Dist: websockets<14.0,>=12.0; extra == "binance"
Provides-Extra: bybit
Requires-Dist: pybit>=5.0.0; extra == "bybit"
Provides-Extra: exchanges
Requires-Dist: python-binance>=1.0.0; extra == "exchanges"
Requires-Dist: pybit>=5.0.0; extra == "exchanges"
Requires-Dist: websockets<14.0,>=12.0; extra == "exchanges"
Provides-Extra: storage
Requires-Dist: pyarrow>=12.0.0; extra == "storage"
Requires-Dist: duckdb>=0.9.0; extra == "storage"
Provides-Extra: stream
Requires-Dist: websockets<14.0,>=12.0; extra == "stream"
Requires-Dist: aiohttp>=3.9.0; extra == "stream"
Provides-Extra: all
Requires-Dist: python-binance>=1.0.0; extra == "all"
Requires-Dist: pybit>=5.0.0; extra == "all"
Requires-Dist: websockets<14.0,>=12.0; extra == "all"
Requires-Dist: aiohttp>=3.9.0; extra == "all"
Requires-Dist: pyarrow>=12.0.0; extra == "all"
Requires-Dist: duckdb>=0.9.0; extra == "all"
Requires-Dist: tenacity>=8.0.0; extra == "all"
Dynamic: license-file
